{
    "behavior": "", 
    "checkable": false, 
    "class": "a", 
    "clickable": true, 
    "content-desc": "", 
    "enabled": false, 
    "focusable": true, 
    "focused": false, 
    "hash": "TFgOFKwCAmtvmScUQIio+g==\n", 
    "height": 22, 
    "hier_level": 0, 
    "human_hash": "a_X626_Y235_W158_H22", 
    "index": -1, 
    "internal": {
        "elem_dict": {
            "attributes": {
                "adhocenable": "false", 
                "href": "/content/travel/en/passports/need-passport/apply-in-person.html", 
                "title": "Apply in Person page"
            }, 
            "background-color": "rgba(0, 0, 0, 0)", 
            "class": "a", 
            "color": "rgb(0, 56, 117)", 
            "domLevel": 11, 
            "flags": {
                "checkable": false, 
                "clickable": true, 
                "enabled": false, 
                "focusable": true, 
                "focused": false, 
                "scrollable": false
            }, 
            "font-family": "robotocondensed-regular-webfont", 
            "font-weight": "400", 
            "fontSize": 16, 
            "height": 22, 
            "identifier": "", 
            "is-focused": false, 
            "is-hidden": false, 
            "name": "", 
            "tagName": "a", 
            "text": "applying for the first time", 
            "type": "", 
            "value": "", 
            "width": 158, 
            "x": 626, 
            "xPercent": 32.58544921875, 
            "y": 235, 
            "yPercent": 8.207897033158813
        }, 
        "location": {
            "x": 626, 
            "y": 235
        }, 
        "size": {
            "height": 22, 
            "width": 158
        }, 
        "tag_name": "a", 
        "text": "applying for the first time"
    }, 
    "is_transformed": true, 
    "package": "", 
    "password": false, 
    "resource-id": "", 
    "scrollable": false, 
    "tag_name": "a", 
    "text": "applying for the first time", 
    "transformed": true, 
    "width": 158, 
    "x": 626, 
    "y": 235
}